tempo/__init__.py
tempo_py-0.0.1.dist-info/LICENSE
tempo_py-0.0.1.dist-info/METADATA
tempo_py-0.0.1.dist-info/WHEEL
tempo_py-0.0.1.dist-info/top_level.txt
tempo_py-0.0.1.dist-info/RECORD
