Metadata-Version: 2.1
Name: tempo-py
Version: 0.0.1
Summary: A python library for working with the National Institute of Statistics Tempo Online Database.
Author: Mark Vereș
Author-email: Mark Vereș <mark@markveres.ro>
Project-URL: Homepage, https://github.com/mark-veres/tempo.py
Project-URL: Issues, https://github.com/mark-veres/tempo.py/issues
Classifier: Programming Language :: Python :: 3
Classifier: License :: OSI Approved :: MIT License
Classifier: Operating System :: OS Independent
Requires-Python: >=3.8
License-File: LICENSE
